{"records": {"expiryDates": ["23-Feb-2023", "29-Mar-2023", "27-Apr-2023"], "data": [{"strikePrice": 1, "expiryDate": "23-Feb-2023", "CE": {"strikePrice": 1, "expiryDate": "23-Feb-2023", "underlying": "IDEA", "identifier": "OPTSTKIDEA23-02-2023CE1.00", "openInterest": 0, "changeinOpenInterest": 0, "pchangeinOpenInterest": 0, "totalTradedVolume": 0, "impliedVolatility": 0, "lastPrice": 0, "change": 0, "pChange": 0, "totalBuyQuantity": 140000, "totalSellQuantity": 2170000, "bidQty": 140000, "bidprice": 4.7, "askQty": 2100000, "askPrice": 9.45, "underlyingValue": 7.2}, "PE": {"strikePrice": 1, "expiryDate": "23-Feb-2023", "underlying": "IDEA", "identifier": "OPTSTKIDEA23-02-2023PE1.00", "openInterest": 0, "changeinOpenInterest": 0, "pchangeinOpenInterest": 0, "totalTradedVolume": 0, "impliedVolatility": 0, "lastPrice": 0, "change": 0, "pChange": 0, "totalBuyQuantity": 0, "totalSellQuantity": 420000, "bidQty": 0, "bidprice": 0, "askQty": 350000, "askPrice": 0.05, "underlyingValue": 7.2}}, {"strikePrice": 1, "expiryDate": "29-Mar-2023", "PE": {"strikePrice": 1, "expiryDate": "29-Mar-2023", "underlying": "IDEA", "identifier": "OPTSTKIDEA29-03-2023PE1.00", "openInterest": 0, "changeinOpenInterest": 0, "pchangeinOpenInterest": 0, "totalTradedVolume": 0, "impliedVolatility": 0, "lastPrice": 0, "change": 0, "pChange": 0, "totalBuyQuantity": 0, "totalSellQuantity": 210000, "bidQty": 0, "bidprice": 0, "askQty": 70000, "askPrice": 0.05, "underlyingValue": 7.2}, "CE": {"strikePrice": 1, "expiryDate": "29-Mar-2023", "underlying": "IDEA", "identifier": "OPTSTKIDEA29-03-2023CE1.00", "openInterest": 0, "changeinOpenInterest": 0, "pchangeinOpenInterest": 0, "totalTradedVolume": 0, "impliedVolatility": 0, "lastPrice": 0, "change": 0, "pChange": 0, "totalBuyQuantity": 2240000, "totalSellQuantity": 2380000, "bidQty": 140000, "bidprice": 4.75, "askQty": 210000, "askPrice": 8.05, "underlyingValue": 7.2}}, {"strikePrice": 1, "expiryDate": "27-Apr-2023", "PE": {"strikePrice": 1, "expiryDate": "27-Apr-2023", "underlying": "IDEA", "identifier": "OPTSTKIDEA27-04-2023PE1.00", "openInterest": 0, "changeinOpenInterest": 0, "pchangeinOpenInterest": 0, "totalTradedVolume": 0, "impliedVolatility": 0, "lastPrice": 0, "change": 0, "pChange": 0, "totalBuyQuantity": 0, "totalSellQuantity": 280000, "bidQty": 0, "bidprice": 0, "askQty": 140000, "askPrice": 0.45, "underlyingValue": 7.2}}, {"strikePrice": 2, "expiryDate": "29-Mar-2023", "PE": {"strikePrice": 2, "expiryDate": "29-Mar-2023", "underlying": "IDEA", "identifier": "OPTSTKIDEA29-03-2023PE2.00", "openInterest": 0, "changeinOpenInterest": 0, "pchangeinOpenInterest": 0, "totalTradedVolume": 0, "impliedVolatility": 0, "lastPrice": 0, "change": 0, "pChange": 0, "totalBuyQuantity": 0, "totalSellQuantity": 210000, "bidQty": 0, "bidprice": 0, "askQty": 70000, "askPrice": 0.05, "underlyingValue": 7.2}, "CE": {"strikePrice": 2, "expiryDate": "29-Mar-2023", "underlying": "IDEA", "identifier": "OPTSTKIDEA29-03-2023CE2.00", "openInterest": 0, "changeinOpenInterest": 0, "pchangeinOpenInterest": 0, "totalTradedVolume": 0, "impliedVolatility": 0, "lastPrice": 0, "change": 0, "pChange": 0, "totalBuyQuantity": 2240000, "totalSellQuantity": 2380000, "bidQty": 140000, "bidprice": 3.75, "askQty": 210000, "askPrice": 7.05, "underlyingValue": 7.2}}, {"strikePrice": 2, "expiryDate": "23-Feb-2023", "CE": {"strikePrice": 2, "expiryDate": "23-Feb-2023", "underlying": "IDEA", "identifier": "OPTSTKIDEA23-02-2023CE2.00", "openInterest": 0, "changeinOpenInterest": 0, "pchangeinOpenInterest": 0, "totalTradedVolume": 0, "impliedVolatility": 0, "lastPrice": 0, "change": 0, "pChange": 0, "totalBuyQuantity": 210000, "totalSellQuantity": 2170000, "bidQty": 140000, "bidprice": 3.7, "askQty": 2100000, "askPrice": 8.45, "underlyingValue": 7.2}, "PE": {"strikePrice": 2, "expiryDate": "23-Feb-2023", "underlying": "IDEA", "identifier": "OPTSTKIDEA23-02-2023PE2.00", "openInterest": 0, "changeinOpenInterest": 0, "pchangeinOpenInterest": 0, "totalTradedVolume": 0, "impliedVolatility": 0, "lastPrice": 0, "change": 0, "pChange": 0, "totalBuyQuantity": 0, "totalSellQuantity": 840000, "bidQty": 0, "bidprice": 0, "askQty": 420000, "askPrice": 0.05, "underlyingValue": 7.2}}, {"strikePrice": 2, "expiryDate": "27-Apr-2023", "PE": {"strikePrice": 2, "expiryDate": "27-Apr-2023", "underlying": "IDEA", "identifier": "OPTSTKIDEA27-04-2023PE2.00", "openInterest": 0, "changeinOpenInterest": 0, "pchangeinOpenInterest": 0, "totalTradedVolume": 0, "impliedVolatility": 0, "lastPrice": 0, "change": 0, "pChange": 0, "totalBuyQuantity": 0, "totalSellQuantity": 280000, "bidQty": 0, "bidprice": 0, "askQty": 70000, "askPrice": 0.2, "underlyingValue": 7.2}}, {"strikePrice": 3, "expiryDate": "23-Feb-2023", "PE": {"strikePrice": 3, "expiryDate": "23-Feb-2023", "underlying": "IDEA", "identifier": "OPTSTKIDEA23-02-2023PE3.00", "openInterest": 9, "changeinOpenInterest": 0, "pchangeinOpenInterest": 0, "totalTradedVolume": 0, "impliedVolatility": 0, "lastPrice": 0.05, "change": 0, "pChange": 0, "totalBuyQuantity": 0, "totalSellQuantity": 2800000, "bidQty": 0, "bidprice": 0, "askQty": 420000, "askPrice": 0.05, "underlyingValue": 7.2}, "CE": {"strikePrice": 3, "expiryDate": "23-Feb-2023", "underlying": "IDEA", "identifier": "OPTSTKIDEA23-02-2023CE3.00", "openInterest": 0, "changeinOpenInterest": 0, "pchangeinOpenInterest": 0, "totalTradedVolume": 0, "impliedVolatility": 0, "lastPrice": 0, "change": 0, "pChange": 0, "totalBuyQuantity": 350000, "totalSellQuantity": 2310000, "bidQty": 140000, "bidprice": 2.7, "askQty": 140000, "askPrice": 5.85, "underlyingValue": 7.2}}, {"strikePrice": 3, "expiryDate": "29-Mar-2023", "CE": {"strikePrice": 3, "expiryDate": "29-Mar-2023", "underlying": "IDEA", "identifier": "OPTSTKIDEA29-03-2023CE3.00", "openInterest": 0, "changeinOpenInterest": 0, "pchangeinOpenInterest": 0, "totalTradedVolume": 0, "impliedVolatility": 0, "lastPrice": 0, "change": 0, "pChange": 0, "totalBuyQuantity": 770000, "totalSellQuantity": 2170000, "bidQty": 140000, "bidprice": 3.05, "askQty": 2100000, "askPrice": 6.1, "underlyingValue": 7.2}, "PE": {"strikePrice": 3, "expiryDate": "29-Mar-2023", "underlying": "IDEA", "identifier": "OPTSTKIDEA29-03-2023PE3.00", "openInterest": 9, "changeinOpenInterest": 0, "pchangeinOpenInterest": 0, "totalTradedVolume": 0, "impliedVolatility": 0, "lastPrice": 0.05, "change": 0, "pChange": 0, "totalBuyQuantity": 0, "totalSellQuantity": 1190000, "bidQty": 0, "bidprice": 0, "askQty": 770000, "askPrice": 0.05, "underlyingValue": 7.2}}, {"strikePrice": 3, "expiryDate": "27-Apr-2023", "PE": {"strikePrice": 3, "expiryDate": "27-Apr-2023", "underlying": "IDEA", "identifier": "OPTSTKIDEA27-04-2023PE3.00", "openInterest": 0, "changeinOpenInterest": 0, "pchangeinOpenInterest": 0, "totalTradedVolume": 0, "impliedVolatility": 0, "lastPrice": 0, "change": 0, "pChange": 0, "totalBuyQuantity": 0, "totalSellQuantity": 350000, "bidQty": 0, "bidprice": 0, "askQty": 70000, "askPrice": 0.1, "underlyingValue": 7.2}, "CE": {"strikePrice": 3, "expiryDate": "27-Apr-2023", "underlying": "IDEA", "identifier": "OPTSTKIDEA27-04-2023CE3.00", "openInterest": 0, "changeinOpenInterest": 0, "pchangeinOpenInterest": 0, "totalTradedVolume": 0, "impliedVolatility": 0, "lastPrice": 0, "change": 0, "pChange": 0, "totalBuyQuantity": 70000, "totalSellQuantity": 0, "bidQty": 70000, "bidprice": 2, "askQty": 0, "askPrice": 0, "underlyingValue": 7.2}}, {"strikePrice": 4, "expiryDate": "29-Mar-2023", "CE": {"strikePrice": 4, "expiryDate": "29-Mar-2023", "underlying": "IDEA", "identifier": "OPTSTKIDEA29-03-2023CE4.00", "openInterest": 0, "changeinOpenInterest": 0, "pchangeinOpenInterest": 0, "totalTradedVolume": 0, "impliedVolatility": 0, "lastPrice": 0, "change": 0, "pChange": 0, "totalBuyQuantity": 1750000, "totalSellQuantity": 2310000, "bidQty": 140000, "bidprice": 2.95, "askQty": 140000, "askPrice": 5.05, "underlyingValue": 7.2}, "PE": {"strikePrice": 4, "expiryDate": "29-Mar-2023", "underlying": "IDEA", "identifier": "OPTSTKIDEA29-03-2023PE4.00", "openInterest": 4, "changeinOpenInterest": 1, "pchangeinOpenInterest": 33.333333333333336, "totalTradedVolume": 1, "impliedVolatility": 115.16, "lastPrice": 0.05, "change": 0, "pChange": 0, "totalBuyQuantity": 0, "totalSellQuantity": 840000, "bidQty": 0, "bidprice": 0, "askQty": 210000, "askPrice": 0.05, "underlyingValue": 7.2}}, {"strikePrice": 4, "expiryDate": "23-Feb-2023", "PE": {"strikePrice": 4, "expiryDate": "23-Feb-2023", "underlying": "IDEA", "identifier": "OPTSTKIDEA23-02-2023PE4.00", "openInterest": 7, "changeinOpenInterest": 0, "pchangeinOpenInterest": 0, "totalTradedVolume": 0, "impliedVolatility": 0, "lastPrice": 0.05, "change": 0, "pChange": 0, "totalBuyQuantity": 0, "totalSellQuantity": 420000, "bidQty": 0, "bidprice": 0, "askQty": 420000, "askPrice": 0.05, "underlyingValue": 7.2}, "CE": {"strikePrice": 4, "expiryDate": "23-Feb-2023", "underlying": "IDEA", "identifier": "OPTSTKIDEA23-02-2023CE4.00", "openInterest": 0, "changeinOpenInterest": 0, "pchangeinOpenInterest": 0, "totalTradedVolume": 0, "impliedVolatility": 0, "lastPrice": 0, "change": 0, "pChange": 0, "totalBuyQuantity": 280000, "totalSellQuantity": 2170000, "bidQty": 140000, "bidprice": 1.7, "askQty": 2100000, "askPrice": 6.5, "underlyingValue": 7.2}}, {"strikePrice": 4, "expiryDate": "27-Apr-2023", "CE": {"strikePrice": 4, "expiryDate": "27-Apr-2023", "underlying": "IDEA", "identifier": "OPTSTKIDEA27-04-2023CE4.00", "openInterest": 0, "changeinOpenInterest": 0, "pchangeinOpenInterest": 0, "totalTradedVolume": 0, "impliedVolatility": 0, "lastPrice": 0, "change": 0, "pChange": 0, "totalBuyQuantity": 210000, "totalSellQuantity": 0, "bidQty": 70000, "bidprice": 1.4, "askQty": 0, "askPrice": 0, "underlyingValue": 7.2}, "PE": {"strikePrice": 4, "expiryDate": "27-Apr-2023", "underlying": "IDEA", "identifier": "OPTSTKIDEA27-04-2023PE4.00", "openInterest": 0, "changeinOpenInterest": 0, "pchangeinOpenInterest": 0, "totalTradedVolume": 0, "impliedVolatility": 0, "lastPrice": 0, "change": 0, "pChange": 0, "totalBuyQuantity": 0, "totalSellQuantity": 490000, "bidQty": 0, "bidprice": 0, "askQty": 70000, "askPrice": 0.2, "underlyingValue": 7.2}}, {"strikePrice": 5, "expiryDate": "23-Feb-2023", "CE": {"strikePrice": 5, "expiryDate": "23-Feb-2023", "underlying": "IDEA", "identifier": "OPTSTKIDEA23-02-2023CE5.00", "openInterest": 0, "changeinOpenInterest": 0, "pchangeinOpenInterest": 0, "totalTradedVolume": 0, "impliedVolatility": 0, "lastPrice": 1.65, "change": 0, "pChange": 0, "totalBuyQuantity": 980000, "totalSellQuantity": 2310000, "bidQty": 140000, "bidprice": 1.05, "askQty": 140000, "askPrice": 4.45, "underlyingValue": 7.2}, "PE": {"strikePrice": 5, "expiryDate": "23-Feb-2023", "underlying": "IDEA", "identifier": "OPTSTKIDEA23-02-2023PE5.00", "openInterest": 214, "changeinOpenInterest": 0, "pchangeinOpenInterest": 0, "totalTradedVolume": 1, "impliedVolatility": 197.58, "lastPrice": 0.05, "change": 0, "pChange": 0, "totalBuyQuantity": 0, "totalSellQuantity": 11130000, "bidQty": 0, "bidprice": 0, "askQty": 8050000, "askPrice": 0.05, "underlyingValue": 7.2}}, {"strikePrice": 5, "expiryDate": "29-Mar-2023", "CE": {"strikePrice": 5, "expiryDate": "29-Mar-2023", "underlying": "IDEA", "identifier": "OPTSTKIDEA29-03-2023CE5.00", "openInterest": 0, "changeinOpenInterest": 0, "pchangeinOpenInterest": 0, "totalTradedVolume": 0, "impliedVolatility": 0, "lastPrice": 0, "change": 0, "pChange": 0, "totalBuyQuantity": 3290000, "totalSellQuantity": 210000, "bidQty": 140000, "bidprice": 0.6, "askQty": 140000, "askPrice": 5.55, "underlyingValue": 7.2}, "PE": {"strikePrice": 5, "expiryDate": "29-Mar-2023", "underlying": "IDEA", "identifier": "OPTSTKIDEA29-03-2023PE5.00", "openInterest": 45, "changeinOpenInterest": 16, "pchangeinOpenInterest": 55.172413793103445, "totalTradedVolume": 17, "impliedVolatility": 78.1, "lastPrice": 0.05, "change": 0, "pChange": 0, "totalBuyQuantity": 0, "totalSellQuantity": 5460000, "bidQty": 0, "bidprice": 0, "askQty": 210000, "askPrice": 0.05, "underlyingValue": 7.2}}, {"strikePrice": 5, "expiryDate": "27-Apr-2023", "PE": {"strikePrice": 5, "expiryDate": "27-Apr-2023", "underlying": "IDEA", "identifier": "OPTSTKIDEA27-04-2023PE5.00", "openInterest": 0, "changeinOpenInterest": 0, "pchangeinOpenInterest": 0, "totalTradedVolume": 0, "impliedVolatility": 0, "lastPrice": 0, "change": 0, "pChange": 0, "totalBuyQuantity": 350000, "totalSellQuantity": 490000, "bidQty": 70000, "bidprice": 0.1, "askQty": 140000, "askPrice": 0.25, "underlyingValue": 7.2}, "CE": {"strikePrice": 5, "expiryDate": "27-Apr-2023", "underlying": "IDEA", "identifier": "OPTSTKIDEA27-04-2023CE5.00", "openInterest": 0, "changeinOpenInterest": 0, "pchangeinOpenInterest": 0, "totalTradedVolume": 0, "impliedVolatility": 0, "lastPrice": 0, "change": 0, "pChange": 0, "totalBuyQuantity": 140000, "totalSellQuantity": 0, "bidQty": 70000, "bidprice": 0.8, "askQty": 0, "askPrice": 0, "underlyingValue": 7.2}}, {"strikePrice": 6, "expiryDate": "23-Feb-2023", "CE": {"strikePrice": 6, "expiryDate": "23-Feb-2023", "underlying": "IDEA", "identifier": "OPTSTKIDEA23-02-2023CE6.00", "openInterest": 102, "changeinOpenInterest": 5, "pchangeinOpenInterest": 5.154639175257732, "totalTradedVolume": 58, "impliedVolatility": 108.9, "lastPrice": 1.25, "change": -0.25, "pChange": -16.666666666666664, "totalBuyQuantity": 10500000, "totalSellQuantity": 2590000, "bidQty": 1960000, "bidprice": 1.15, "askQty": 350000, "askPrice": 1.3, "underlyingValue": 7.2}, "PE": {"strikePrice": 6, "expiryDate": "23-Feb-2023", "underlying": "IDEA", "identifier": "OPTSTKIDEA23-02-2023PE6.00", "openInterest": 607, "changeinOpenInterest": 35, "pchangeinOpenInterest": 6.118881118881119, "totalTradedVolume": 38, "impliedVolatility": 115.56, "lastPrice": 0.05, "change": 0, "pChange": 0, "totalBuyQuantity": 0, "totalSellQuantity": 39060000, "bidQty": 0, "bidprice": 0, "askQty": 22400000, "askPrice": 0.05, "underlyingValue": 7.2}}, {"strikePrice": 6, "expiryDate": "29-Mar-2023", "PE": {"strikePrice": 6, "expiryDate": "29-Mar-2023", "underlying": "IDEA", "identifier": "OPTSTKIDEA29-03-2023PE6.00", "openInterest": 105, "changeinOpenInterest": 32, "pchangeinOpenInterest": 43.83561643835616, "totalTradedVolume": 118, "impliedVolatility": 66.52, "lastPrice": 0.15, "change": 0, "pChange": 0, "totalBuyQuantity": 21490000, "totalSellQuantity": 15470000, "bidQty": 14560000, "bidprice": 0.1, "askQty": 2240000, "askPrice": 0.15, "underlyingValue": 7.2}, "CE": {"strikePrice": 6, "expiryDate": "29-Mar-2023", "underlying": "IDEA", "identifier": "OPTSTKIDEA29-03-2023CE6.00", "openInterest": 15, "changeinOpenInterest": 2, "pchangeinOpenInterest": 15.384615384615385, "totalTradedVolume": 3, "impliedVolatility": 63.84, "lastPrice": 1.4, "change": -0.20000000000000018, "pChange": -12.50000000000001, "totalBuyQuantity": 910000, "totalSellQuantity": 1050000, "bidQty": 70000, "bidprice": 1.3, "askQty": 140000, "askPrice": 1.55, "underlyingValue": 7.2}}, {"strikePrice": 6, "expiryDate": "27-Apr-2023", "CE": {"strikePrice": 6, "expiryDate": "27-Apr-2023", "underlying": "IDEA", "identifier": "OPTSTKIDEA27-04-2023CE6.00", "openInterest": 0, "changeinOpenInterest": 0, "pchangeinOpenInterest": 0, "totalTradedVolume": 0, "impliedVolatility": 0, "lastPrice": 0, "change": 0, "pChange": 0, "totalBuyQuantity": 280000, "totalSellQuantity": 0, "bidQty": 70000, "bidprice": 0.9, "askQty": 0, "askPrice": 0, "underlyingValue": 7.2}, "PE": {"strikePrice": 6, "expiryDate": "27-Apr-2023", "underlying": "IDEA", "identifier": "OPTSTKIDEA27-04-2023PE6.00", "openInterest": 17, "changeinOpenInterest": 4, "pchangeinOpenInterest": 30.76923076923077, "totalTradedVolume": 4, "impliedVolatility": 64.29, "lastPrice": 0.25, "change": 0, "pChange": 0, "totalBuyQuantity": 630000, "totalSellQuantity": 840000, "bidQty": 70000, "bidprice": 0.25, "askQty": 280000, "askPrice": 0.3, "underlyingValue": 7.2}}, {"strikePrice": 7, "expiryDate": "23-Feb-2023", "PE": {"strikePrice": 7, "expiryDate": "23-Feb-2023", "underlying": "IDEA", "identifier": "OPTSTKIDEA23-02-2023PE7.00", "openInterest": 640, "changeinOpenInterest": -237, "pchangeinOpenInterest": -27.02394526795895, "totalTradedVolume": 1539, "impliedVolatility": 51.56, "lastPrice": 0.1, "change": 0, "pChange": 0, "totalBuyQuantity": 46620000, "totalSellQuantity": 35840000, "bidQty": 46620000, "bidprice": 0.05, "askQty": 4200000, "askPrice": 0.1, "underlyingValue": 7.2}, "CE": {"strikePrice": 7, "expiryDate": "23-Feb-2023", "underlying": "IDEA", "identifier": "OPTSTKIDEA23-02-2023CE7.00", "openInterest": 469, "changeinOpenInterest": 92, "pchangeinOpenInterest": 24.40318302387268, "totalTradedVolume": 445, "impliedVolatility": 48.02, "lastPrice": 0.3, "change": -0.25000000000000006, "pChange": -45.45454545454546, "totalBuyQuantity": 25550000, "totalSellQuantity": 6860000, "bidQty": 2730000, "bidprice": 0.25, "askQty": 910000, "askPrice": 0.3, "underlyingValue": 7.2}}, {"strikePrice": 7, "expiryDate": "29-Mar-2023", "CE": {"strikePrice": 7, "expiryDate": "29-Mar-2023", "underlying": "IDEA", "identifier": "OPTSTKIDEA29-03-2023CE7.00", "openInterest": 168, "changeinOpenInterest": 84, "pchangeinOpenInterest": 100, "totalTradedVolume": 227, "impliedVolatility": 59.17, "lastPrice": 0.7, "change": -0.20000000000000007, "pChange": -22.22222222222223, "totalBuyQuantity": 22960000, "totalSellQuantity": 2380000, "bidQty": 2100000, "bidprice": 0.65, "askQty": 350000, "askPrice": 0.7, "underlyingValue": 7.2}, "PE": {"strikePrice": 7, "expiryDate": "29-Mar-2023", "underlying": "IDEA", "identifier": "OPTSTKIDEA29-03-2023PE7.00", "openInterest": 344, "changeinOpenInterest": 125, "pchangeinOpenInterest": 57.077625570776256, "totalTradedVolume": 260, "impliedVolatility": 56.56, "lastPrice": 0.4, "change": 0.10000000000000003, "pChange": 33.33333333333335, "totalBuyQuantity": 21000000, "totalSellQuantity": 12040000, "bidQty": 5390000, "bidprice": 0.35, "askQty": 630000, "askPrice": 0.4, "underlyingValue": 7.2}}, {"strikePrice": 7, "expiryDate": "27-Apr-2023", "PE": {"strikePrice": 7, "expiryDate": "27-Apr-2023", "underlying": "IDEA", "identifier": "OPTSTKIDEA27-04-2023PE7.00", "openInterest": 0, "changeinOpenInterest": 0, "pchangeinOpenInterest": 0, "totalTradedVolume": 0, "impliedVolatility": 0, "lastPrice": 0, "change": 0, "pChange": 0, "totalBuyQuantity": 560000, "totalSellQuantity": 350000, "bidQty": 70000, "bidprice": 0.6, "askQty": 70000, "askPrice": 0.75, "underlyingValue": 7.2}, "CE": {"strikePrice": 7, "expiryDate": "27-Apr-2023", "underlying": "IDEA", "identifier": "OPTSTKIDEA27-04-2023CE7.00", "openInterest": 0, "changeinOpenInterest": 0, "pchangeinOpenInterest": 0, "totalTradedVolume": 0, "impliedVolatility": 0, "lastPrice": 0, "change": 0, "pChange": 0, "totalBuyQuantity": 420000, "totalSellQuantity": 630000, "bidQty": 70000, "bidprice": 0.8, "askQty": 70000, "askPrice": 1.15, "underlyingValue": 7.2}}, {"strikePrice": 8, "expiryDate": "23-Feb-2023", "PE": {"strikePrice": 8, "expiryDate": "23-Feb-2023", "underlying": "IDEA", "identifier": "OPTSTKIDEA23-02-2023PE8.00", "openInterest": 741, "changeinOpenInterest": -88, "pchangeinOpenInterest": -10.615199034981906, "totalTradedVolume": 182, "impliedVolatility": 52.09, "lastPrice": 0.8, "change": 0.20000000000000007, "pChange": 33.33333333333335, "totalBuyQuantity": 14070000, "totalSellQuantity": 6720000, "bidQty": 140000, "bidprice": 0.8, "askQty": 70000, "askPrice": 0.85, "underlyingValue": 7.2}, "CE": {"strikePrice": 8, "expiryDate": "23-Feb-2023", "underlying": "IDEA", "identifier": "OPTSTKIDEA23-02-2023CE8.00", "openInterest": 1288, "changeinOpenInterest": -113, "pchangeinOpenInterest": -8.065667380442541, "totalTradedVolume": 1167, "impliedVolatility": 74, "lastPrice": 0.05, "change": -0.05, "pChange": -50, "totalBuyQuantity": 1260000, "totalSellQuantity": 60900000, "bidQty": 1260000, "bidprice": 0.05, "askQty": 35700000, "askPrice": 0.1, "underlyingValue": 7.2}}, {"strikePrice": 8, "expiryDate": "27-Apr-2023", "CE": {"strikePrice": 8, "expiryDate": "27-Apr-2023", "underlying": "IDEA", "identifier": "OPTSTKIDEA27-04-2023CE8.00", "openInterest": 29, "changeinOpenInterest": 1, "pchangeinOpenInterest": 3.5714285714285716, "totalTradedVolume": 2, "impliedVolatility": 72.32, "lastPrice": 0.65, "change": 0, "pChange": 0, "totalBuyQuantity": 2800000, "totalSellQuantity": 2240000, "bidQty": 280000, "bidprice": 0.55, "askQty": 210000, "askPrice": 0.65, "underlyingValue": 7.2}, "PE": {"strikePrice": 8, "expiryDate": "27-Apr-2023", "underlying": "IDEA", "identifier": "OPTSTKIDEA27-04-2023PE8.00", "openInterest": 0, "changeinOpenInterest": 0, "pchangeinOpenInterest": 0, "totalTradedVolume": 0, "impliedVolatility": 0, "lastPrice": 0, "change": 0, "pChange": 0, "totalBuyQuantity": 280000, "totalSellQuantity": 140000, "bidQty": 70000, "bidprice": 0.8, "askQty": 70000, "askPrice": 4.05, "underlyingValue": 7.2}}, {"strikePrice": 8, "expiryDate": "29-Mar-2023", "PE": {"strikePrice": 8, "expiryDate": "29-Mar-2023", "underlying": "IDEA", "identifier": "OPTSTKIDEA29-03-2023PE8.00", "openInterest": 178, "changeinOpenInterest": 3, "pchangeinOpenInterest": 1.7142857142857142, "totalTradedVolume": 37, "impliedVolatility": 63.35, "lastPrice": 1.05, "change": 0.20000000000000007, "pChange": 23.52941176470589, "totalBuyQuantity": 7070000, "totalSellQuantity": 4130000, "bidQty": 140000, "bidprice": 1.05, "askQty": 1540000, "askPrice": 1.1, "underlyingValue": 7.2}, "CE": {"strikePrice": 8, "expiryDate": "29-Mar-2023", "underlying": "IDEA", "identifier": "OPTSTKIDEA29-03-2023CE8.00", "openInterest": 549, "changeinOpenInterest": 172, "pchangeinOpenInterest": 45.62334217506631, "totalTradedVolume": 722, "impliedVolatility": 64.77, "lastPrice": 0.35, "change": -0.10000000000000003, "pChange": -22.22222222222223, "totalBuyQuantity": 40880000, "totalSellQuantity": 19600000, "bidQty": 9380000, "bidprice": 0.3, "askQty": 140000, "askPrice": 0.35, "underlyingValue": 7.2}}, {"strikePrice": 9, "expiryDate": "23-Feb-2023", "CE": {"strikePrice": 9, "expiryDate": "23-Feb-2023", "underlying": "IDEA", "identifier": "OPTSTKIDEA23-02-2023CE9.00", "openInterest": 1641, "changeinOpenInterest": 14, "pchangeinOpenInterest": 0.860479409956976, "totalTradedVolume": 64, "impliedVolatility": 125.6, "lastPrice": 0.05, "change": 0, "pChange": 0, "totalBuyQuantity": 0, "totalSellQuantity": 48720000, "bidQty": 0, "bidprice": 0, "askQty": 32340000, "askPrice": 0.05, "underlyingValue": 7.2}, "PE": {"strikePrice": 9, "expiryDate": "23-Feb-2023", "underlying": "IDEA", "identifier": "OPTSTKIDEA23-02-2023PE9.00", "openInterest": 235, "changeinOpenInterest": -53, "pchangeinOpenInterest": -18.40277777777778, "totalTradedVolume": 75, "impliedVolatility": 96.8, "lastPrice": 1.8, "change": 0.25, "pChange": 16.129032258064516, "totalBuyQuantity": 8050000, "totalSellQuantity": 6020000, "bidQty": 280000, "bidprice": 1.75, "askQty": 280000, "askPrice": 1.85, "underlyingValue": 7.2}}, {"strikePrice": 9, "expiryDate": "29-Mar-2023", "CE": {"strikePrice": 9, "expiryDate": "29-Mar-2023", "underlying": "IDEA", "identifier": "OPTSTKIDEA29-03-2023CE9.00", "openInterest": 303, "changeinOpenInterest": 72, "pchangeinOpenInterest": 31.16883116883117, "totalTradedVolume": 187, "impliedVolatility": 72.81, "lastPrice": 0.2, "change": 0, "pChange": 0, "totalBuyQuantity": 22260000, "totalSellQuantity": 18270000, "bidQty": 6860000, "bidprice": 0.15, "askQty": 6790000, "askPrice": 0.2, "underlyingValue": 7.2}, "PE": {"strikePrice": 9, "expiryDate": "29-Mar-2023", "underlying": "IDEA", "identifier": "OPTSTKIDEA29-03-2023PE9.00", "openInterest": 126, "changeinOpenInterest": 16, "pchangeinOpenInterest": 14.545454545454545, "totalTradedVolume": 16, "impliedVolatility": 65.2, "lastPrice": 1.85, "change": 0.25, "pChange": 15.625, "totalBuyQuantity": 700000, "totalSellQuantity": 280000, "bidQty": 70000, "bidprice": 1.85, "askQty": 70000, "askPrice": 1.9, "underlyingValue": 7.2}}, {"strikePrice": 9, "expiryDate": "27-Apr-2023", "PE": {"strikePrice": 9, "expiryDate": "27-Apr-2023", "underlying": "IDEA", "identifier": "OPTSTKIDEA27-04-2023PE9.00", "openInterest": 0, "changeinOpenInterest": 0, "pchangeinOpenInterest": 0, "totalTradedVolume": 0, "impliedVolatility": 0, "lastPrice": 0, "change": 0, "pChange": 0, "totalBuyQuantity": 700000, "totalSellQuantity": 0, "bidQty": 70000, "bidprice": 0.6, "askQty": 0, "askPrice": 0, "underlyingValue": 7.2}, "CE": {"strikePrice": 9, "expiryDate": "27-Apr-2023", "underlying": "IDEA", "identifier": "OPTSTKIDEA27-04-2023CE9.00", "openInterest": 8, "changeinOpenInterest": 3, "pchangeinOpenInterest": 60, "totalTradedVolume": 3, "impliedVolatility": 68.92, "lastPrice": 0.35, "change": -0.10000000000000003, "pChange": -22.22222222222223, "totalBuyQuantity": 1120000, "totalSellQuantity": 420000, "bidQty": 140000, "bidprice": 0.35, "askQty": 70000, "askPrice": 0.4, "underlyingValue": 7.2}}, {"strikePrice": 10, "expiryDate": "23-Feb-2023", "PE": {"strikePrice": 10, "expiryDate": "23-Feb-2023", "underlying": "IDEA", "identifier": "OPTSTKIDEA23-02-2023PE10.00", "openInterest": 52, "changeinOpenInterest": 0, "pchangeinOpenInterest": 0, "totalTradedVolume": 0, "impliedVolatility": 0, "lastPrice": 2.2, "change": 0, "pChange": 0, "totalBuyQuantity": 3290000, "totalSellQuantity": 280000, "bidQty": 70000, "bidprice": 2.75, "askQty": 140000, "askPrice": 4.6, "underlyingValue": 7.2}, "CE": {"strikePrice": 10, "expiryDate": "23-Feb-2023", "underlying": "IDEA", "identifier": "OPTSTKIDEA23-02-2023CE10.00", "openInterest": 1336, "changeinOpenInterest": 6, "pchangeinOpenInterest": 0.45112781954887216, "totalTradedVolume": 15, "impliedVolatility": 167.11, "lastPrice": 0.05, "change": 0, "pChange": 0, "totalBuyQuantity": 0, "totalSellQuantity": 34720000, "bidQty": 0, "bidprice": 0, "askQty": 24290000, "askPrice": 0.05, "underlyingValue": 7.2}}, {"strikePrice": 10, "expiryDate": "29-Mar-2023", "CE": {"strikePrice": 10, "expiryDate": "29-Mar-2023", "underlying": "IDEA", "identifier": "OPTSTKIDEA29-03-2023CE10.00", "openInterest": 355, "changeinOpenInterest": -3, "pchangeinOpenInterest": -0.8379888268156425, "totalTradedVolume": 126, "impliedVolatility": 75.16, "lastPrice": 0.1, "change": -0.04999999999999999, "pChange": -33.33333333333333, "totalBuyQuantity": 12040000, "totalSellQuantity": 22330000, "bidQty": 2380000, "bidprice": 0.1, "askQty": 12810000, "askPrice": 0.15, "underlyingValue": 7.2}, "PE": {"strikePrice": 10, "expiryDate": "29-Mar-2023", "underlying": "IDEA", "identifier": "OPTSTKIDEA29-03-2023PE10.00", "openInterest": 48, "changeinOpenInterest": 2, "pchangeinOpenInterest": 4.3478260869565215, "totalTradedVolume": 2, "impliedVolatility": 65.79, "lastPrice": 2.75, "change": 0.2999999999999998, "pChange": 12.244897959183664, "totalBuyQuantity": 1330000, "totalSellQuantity": 2240000, "bidQty": 70000, "bidprice": 2.75, "askQty": 70000, "askPrice": 2.9, "underlyingValue": 7.2}}, {"strikePrice": 10, "expiryDate": "27-Apr-2023", "PE": {"strikePrice": 10, "expiryDate": "27-Apr-2023", "underlying": "IDEA", "identifier": "OPTSTKIDEA27-04-2023PE10.00", "openInterest": 0, "changeinOpenInterest": 0, "pchangeinOpenInterest": 0, "totalTradedVolume": 0, "impliedVolatility": 0, "lastPrice": 0, "change": 0, "pChange": 0, "totalBuyQuantity": 980000, "totalSellQuantity": 0, "bidQty": 70000, "bidprice": 0.6, "askQty": 0, "askPrice": 0, "underlyingValue": 7.2}, "CE": {"strikePrice": 10, "expiryDate": "27-Apr-2023", "underlying": "IDEA", "identifier": "OPTSTKIDEA27-04-2023CE10.00", "openInterest": 20, "changeinOpenInterest": 1, "pchangeinOpenInterest": 5.2631578947368425, "totalTradedVolume": 5, "impliedVolatility": 75.09, "lastPrice": 0.25, "change": -0.04999999999999999, "pChange": -16.666666666666664, "totalBuyQuantity": 1120000, "totalSellQuantity": 980000, "bidQty": 560000, "bidprice": 0.2, "askQty": 280000, "askPrice": 0.25, "underlyingValue": 7.2}}, {"strikePrice": 11, "expiryDate": "23-Feb-2023", "PE": {"strikePrice": 11, "expiryDate": "23-Feb-2023", "underlying": "IDEA", "identifier": "OPTSTKIDEA23-02-2023PE11.00", "openInterest": 1, "changeinOpenInterest": 0, "pchangeinOpenInterest": 0, "totalTradedVolume": 0, "impliedVolatility": 0, "lastPrice": 3.85, "change": 0, "pChange": 0, "totalBuyQuantity": 980000, "totalSellQuantity": 210000, "bidQty": 840000, "bidprice": 1.05, "askQty": 210000, "askPrice": 6.5, "underlyingValue": 7.2}, "CE": {"strikePrice": 11, "expiryDate": "23-Feb-2023", "underlying": "IDEA", "identifier": "OPTSTKIDEA23-02-2023CE11.00", "openInterest": 463, "changeinOpenInterest": 3, "pchangeinOpenInterest": 0.6521739130434783, "totalTradedVolume": 3, "impliedVolatility": 202.38, "lastPrice": 0.05, "change": 0, "pChange": 0, "totalBuyQuantity": 0, "totalSellQuantity": 16730000, "bidQty": 0, "bidprice": 0, "askQty": 13230000, "askPrice": 0.05, "underlyingValue": 7.2}}, {"strikePrice": 11, "expiryDate": "29-Mar-2023", "PE": {"strikePrice": 11, "expiryDate": "29-Mar-2023", "underlying": "IDEA", "identifier": "OPTSTKIDEA29-03-2023PE11.00", "openInterest": 0, "changeinOpenInterest": 0, "pchangeinOpenInterest": 0, "totalTradedVolume": 0, "impliedVolatility": 0, "lastPrice": 0, "change": 0, "pChange": 0, "totalBuyQuantity": 490000, "totalSellQuantity": 2100000, "bidQty": 490000, "bidprice": 1.9, "askQty": 2100000, "askPrice": 5.85, "underlyingValue": 7.2}, "CE": {"strikePrice": 11, "expiryDate": "29-Mar-2023", "underlying": "IDEA", "identifier": "OPTSTKIDEA29-03-2023CE11.00", "openInterest": 92, "changeinOpenInterest": 0, "pchangeinOpenInterest": 0, "totalTradedVolume": 9, "impliedVolatility": 77.08, "lastPrice": 0.05, "change": -0.05, "pChange": -50, "totalBuyQuantity": 5390000, "totalSellQuantity": 10220000, "bidQty": 5390000, "bidprice": 0.05, "askQty": 6160000, "askPrice": 0.1, "underlyingValue": 7.2}}, {"strikePrice": 11, "expiryDate": "27-Apr-2023", "CE": {"strikePrice": 11, "expiryDate": "27-Apr-2023", "underlying": "IDEA", "identifier": "OPTSTKIDEA27-04-2023CE11.00", "openInterest": 0, "changeinOpenInterest": 0, "pchangeinOpenInterest": 0, "totalTradedVolume": 0, "impliedVolatility": 0, "lastPrice": 0, "change": 0, "pChange": 0, "totalBuyQuantity": 140000, "totalSellQuantity": 210000, "bidQty": 140000, "bidprice": 0.05, "askQty": 70000, "askPrice": 0.25, "underlyingValue": 7.2}, "PE": {"strikePrice": 11, "expiryDate": "27-Apr-2023", "underlying": "IDEA", "identifier": "OPTSTKIDEA27-04-2023PE11.00", "openInterest": 0, "changeinOpenInterest": 0, "pchangeinOpenInterest": 0, "totalTradedVolume": 0, "impliedVolatility": 0, "lastPrice": 0, "change": 0, "pChange": 0, "totalBuyQuantity": 70000, "totalSellQuantity": 0, "bidQty": 70000, "bidprice": 1.1, "askQty": 0, "askPrice": 0, "underlyingValue": 7.2}}, {"strikePrice": 12, "expiryDate": "23-Feb-2023", "PE": {"strikePrice": 12, "expiryDate": "23-Feb-2023", "underlying": "IDEA", "identifier": "OPTSTKIDEA23-02-2023PE12.00", "openInterest": 0, "changeinOpenInterest": 0, "pchangeinOpenInterest": 0, "totalTradedVolume": 0, "impliedVolatility": 0, "lastPrice": 0, "change": 0, "pChange": 0, "totalBuyQuantity": 280000, "totalSellQuantity": 210000, "bidQty": 140000, "bidprice": 2.6, "askQty": 210000, "askPrice": 7.5, "underlyingValue": 7.2}, "CE": {"strikePrice": 12, "expiryDate": "23-Feb-2023", "underlying": "IDEA", "identifier": "OPTSTKIDEA23-02-2023CE12.00", "openInterest": 358, "changeinOpenInterest": 0, "pchangeinOpenInterest": 0, "totalTradedVolume": 0, "impliedVolatility": 0, "lastPrice": 0.05, "change": 0, "pChange": 0, "totalBuyQuantity": 0, "totalSellQuantity": 11130000, "bidQty": 0, "bidprice": 0, "askQty": 8680000, "askPrice": 0.05, "underlyingValue": 7.2}}, {"strikePrice": 12, "expiryDate": "29-Mar-2023", "PE": {"strikePrice": 12, "expiryDate": "29-Mar-2023", "underlying": "IDEA", "identifier": "OPTSTKIDEA29-03-2023PE12.00", "openInterest": 0, "changeinOpenInterest": 0, "pchangeinOpenInterest": 0, "totalTradedVolume": 0, "impliedVolatility": 0, "lastPrice": 0, "change": 0, "pChange": 0, "totalBuyQuantity": 2240000, "totalSellQuantity": 2100000, "bidQty": 140000, "bidprice": 3, "askQty": 2100000, "askPrice": 6.85, "underlyingValue": 7.2}, "CE": {"strikePrice": 12, "expiryDate": "29-Mar-2023", "underlying": "IDEA", "identifier": "OPTSTKIDEA29-03-2023CE12.00", "openInterest": 65, "changeinOpenInterest": 13, "pchangeinOpenInterest": 25, "totalTradedVolume": 48, "impliedVolatility": 89.06, "lastPrice": 0.05, "change": -0.05, "pChange": -50, "totalBuyQuantity": 70000, "totalSellQuantity": 7770000, "bidQty": 70000, "bidprice": 0.05, "askQty": 3990000, "askPrice": 0.1, "underlyingValue": 7.2}}, {"strikePrice": 12, "expiryDate": "27-Apr-2023", "CE": {"strikePrice": 12, "expiryDate": "27-Apr-2023", "underlying": "IDEA", "identifier": "OPTSTKIDEA27-04-2023CE12.00", "openInterest": 4, "changeinOpenInterest": 0, "pchangeinOpenInterest": 0, "totalTradedVolume": 1, "impliedVolatility": 86.03, "lastPrice": 0.15, "change": 0, "pChange": 0, "totalBuyQuantity": 770000, "totalSellQuantity": 1260000, "bidQty": 70000, "bidprice": 0.1, "askQty": 140000, "askPrice": 0.15, "underlyingValue": 7.2}, "PE": {"strikePrice": 12, "expiryDate": "27-Apr-2023", "underlying": "IDEA", "identifier": "OPTSTKIDEA27-04-2023PE12.00", "openInterest": 0, "changeinOpenInterest": 0, "pchangeinOpenInterest": 0, "totalTradedVolume": 0, "impliedVolatility": 0, "lastPrice": 0, "change": 0, "pChange": 0, "totalBuyQuantity": 70000, "totalSellQuantity": 0, "bidQty": 70000, "bidprice": 1.5, "askQty": 0, "askPrice": 0, "underlyingValue": 7.2}}, {"strikePrice": 13, "expiryDate": "23-Feb-2023", "PE": {"strikePrice": 13, "expiryDate": "23-Feb-2023", "underlying": "IDEA", "identifier": "OPTSTKIDEA23-02-2023PE13.00", "openInterest": 1, "changeinOpenInterest": 0, "pchangeinOpenInterest": 0, "totalTradedVolume": 0, "impliedVolatility": 0, "lastPrice": 5.55, "change": 0, "pChange": 0, "totalBuyQuantity": 2380000, "totalSellQuantity": 420000, "bidQty": 70000, "bidprice": 5.4, "askQty": 140000, "askPrice": 6.2, "underlyingValue": 7.2}, "CE": {"strikePrice": 13, "expiryDate": "23-Feb-2023", "underlying": "IDEA", "identifier": "OPTSTKIDEA23-02-2023CE13.00", "openInterest": 196, "changeinOpenInterest": 1, "pchangeinOpenInterest": 0.5128205128205128, "totalTradedVolume": 1, "impliedVolatility": 260.61, "lastPrice": 0.05, "change": 0, "pChange": 0, "totalBuyQuantity": 0, "totalSellQuantity": 5950000, "bidQty": 0, "bidprice": 0, "askQty": 3640000, "askPrice": 0.05, "underlyingValue": 7.2}}, {"strikePrice": 13, "expiryDate": "29-Mar-2023", "CE": {"strikePrice": 13, "expiryDate": "29-Mar-2023", "underlying": "IDEA", "identifier": "OPTSTKIDEA29-03-2023CE13.00", "openInterest": 80, "changeinOpenInterest": 0, "pchangeinOpenInterest": 0, "totalTradedVolume": 0, "impliedVolatility": 0, "lastPrice": 0.05, "change": 0, "pChange": 0, "totalBuyQuantity": 0, "totalSellQuantity": 6650000, "bidQty": 0, "bidprice": 0, "askQty": 2170000, "askPrice": 0.05, "underlyingValue": 7.2}, "PE": {"strikePrice": 13, "expiryDate": "29-Mar-2023", "underlying": "IDEA", "identifier": "OPTSTKIDEA29-03-2023PE13.00", "openInterest": 0, "changeinOpenInterest": 0, "pchangeinOpenInterest": 0, "totalTradedVolume": 0, "impliedVolatility": 0, "lastPrice": 0, "change": 0, "pChange": 0, "totalBuyQuantity": 2310000, "totalSellQuantity": 2100000, "bidQty": 210000, "bidprice": 4.05, "askQty": 2100000, "askPrice": 7.9, "underlyingValue": 7.2}}, {"strikePrice": 13, "expiryDate": "27-Apr-2023", "CE": {"strikePrice": 13, "expiryDate": "27-Apr-2023", "underlying": "IDEA", "identifier": "OPTSTKIDEA27-04-2023CE13.00", "openInterest": 0, "changeinOpenInterest": 0, "pchangeinOpenInterest": 0, "totalTradedVolume": 0, "impliedVolatility": 0, "lastPrice": 0, "change": 0, "pChange": 0, "totalBuyQuantity": 70000, "totalSellQuantity": 630000, "bidQty": 70000, "bidprice": 0.05, "askQty": 140000, "askPrice": 0.15, "underlyingValue": 7.2}}, {"strikePrice": 14, "expiryDate": "23-Feb-2023", "PE": {"strikePrice": 14, "expiryDate": "23-Feb-2023", "underlying": "IDEA", "identifier": "OPTSTKIDEA23-02-2023PE14.00", "openInterest": 0, "changeinOpenInterest": 0, "pchangeinOpenInterest": 0, "totalTradedVolume": 0, "impliedVolatility": 0, "lastPrice": 0, "change": 0, "pChange": 0, "totalBuyQuantity": 2240000, "totalSellQuantity": 210000, "bidQty": 140000, "bidprice": 5.05, "askQty": 140000, "askPrice": 8.6, "underlyingValue": 7.2}, "CE": {"strikePrice": 14, "expiryDate": "23-Feb-2023", "underlying": "IDEA", "identifier": "OPTSTKIDEA23-02-2023CE14.00", "openInterest": 192, "changeinOpenInterest": 0, "pchangeinOpenInterest": 0, "totalTradedVolume": 0, "impliedVolatility": 0, "lastPrice": 0.05, "change": 0, "pChange": 0, "totalBuyQuantity": 0, "totalSellQuantity": 7280000, "bidQty": 0, "bidprice": 0, "askQty": 5110000, "askPrice": 0.05, "underlyingValue": 7.2}}], "timestamp": "17-Feb-2023 15:30:00", "underlyingValue": 7.2, "strikePrices": [1, 2, 3, 4, 5, 6, 7, 8, 9, 10, 11, 12, 13, 14]}, "filtered": {"data": [{"strikePrice": 1, "expiryDate": "23-Feb-2023", "CE": {"strikePrice": 1, "expiryDate": "23-Feb-2023", "underlying": "IDEA", "identifier": "OPTSTKIDEA23-02-2023CE1.00", "openInterest": 0, "changeinOpenInterest": 0, "pchangeinOpenInterest": 0, "totalTradedVolume": 0, "impliedVolatility": 0, "lastPrice": 0, "change": 0, "pChange": 0, "totalBuyQuantity": 140000, "totalSellQuantity": 2170000, "bidQty": 140000, "bidprice": 4.7, "askQty": 2100000, "askPrice": 9.45, "underlyingValue": 7.2}, "PE": {"strikePrice": 1, "expiryDate": "23-Feb-2023", "underlying": "IDEA", "identifier": "OPTSTKIDEA23-02-2023PE1.00", "openInterest": 0, "changeinOpenInterest": 0, "pchangeinOpenInterest": 0, "totalTradedVolume": 0, "impliedVolatility": 0, "lastPrice": 0, "change": 0, "pChange": 0, "totalBuyQuantity": 0, "totalSellQuantity": 420000, "bidQty": 0, "bidprice": 0, "askQty": 350000, "askPrice": 0.05, "underlyingValue": 7.2}}, {"strikePrice": 2, "expiryDate": "23-Feb-2023", "CE": {"strikePrice": 2, "expiryDate": "23-Feb-2023", "underlying": "IDEA", "identifier": "OPTSTKIDEA23-02-2023CE2.00", "openInterest": 0, "changeinOpenInterest": 0, "pchangeinOpenInterest": 0, "totalTradedVolume": 0, "impliedVolatility": 0, "lastPrice": 0, "change": 0, "pChange": 0, "totalBuyQuantity": 210000, "totalSellQuantity": 2170000, "bidQty": 140000, "bidprice": 3.7, "askQty": 2100000, "askPrice": 8.45, "underlyingValue": 7.2}, "PE": {"strikePrice": 2, "expiryDate": "23-Feb-2023", "underlying": "IDEA", "identifier": "OPTSTKIDEA23-02-2023PE2.00", "openInterest": 0, "changeinOpenInterest": 0, "pchangeinOpenInterest": 0, "totalTradedVolume": 0, "impliedVolatility": 0, "lastPrice": 0, "change": 0, "pChange": 0, "totalBuyQuantity": 0, "totalSellQuantity": 840000, "bidQty": 0, "bidprice": 0, "askQty": 420000, "askPrice": 0.05, "underlyingValue": 7.2}}, {"strikePrice": 3, "expiryDate": "23-Feb-2023", "PE": {"strikePrice": 3, "expiryDate": "23-Feb-2023", "underlying": "IDEA", "identifier": "OPTSTKIDEA23-02-2023PE3.00", "openInterest": 9, "changeinOpenInterest": 0, "pchangeinOpenInterest": 0, "totalTradedVolume": 0, "impliedVolatility": 0, "lastPrice": 0.05, "change": 0, "pChange": 0, "totalBuyQuantity": 0, "totalSellQuantity": 2800000, "bidQty": 0, "bidprice": 0, "askQty": 420000, "askPrice": 0.05, "underlyingValue": 7.2}, "CE": {"strikePrice": 3, "expiryDate": "23-Feb-2023", "underlying": "IDEA", "identifier": "OPTSTKIDEA23-02-2023CE3.00", "openInterest": 0, "changeinOpenInterest": 0, "pchangeinOpenInterest": 0, "totalTradedVolume": 0, "impliedVolatility": 0, "lastPrice": 0, "change": 0, "pChange": 0, "totalBuyQuantity": 350000, "totalSellQuantity": 2310000, "bidQty": 140000, "bidprice": 2.7, "askQty": 140000, "askPrice": 5.85, "underlyingValue": 7.2}}, {"strikePrice": 4, "expiryDate": "23-Feb-2023", "PE": {"strikePrice": 4, "expiryDate": "23-Feb-2023", "underlying": "IDEA", "identifier": "OPTSTKIDEA23-02-2023PE4.00", "openInterest": 7, "changeinOpenInterest": 0, "pchangeinOpenInterest": 0, "totalTradedVolume": 0, "impliedVolatility": 0, "lastPrice": 0.05, "change": 0, "pChange": 0, "totalBuyQuantity": 0, "totalSellQuantity": 420000, "bidQty": 0, "bidprice": 0, "askQty": 420000, "askPrice": 0.05, "underlyingValue": 7.2}, "CE": {"strikePrice": 4, "expiryDate": "23-Feb-2023", "underlying": "IDEA", "identifier": "OPTSTKIDEA23-02-2023CE4.00", "openInterest": 0, "changeinOpenInterest": 0, "pchangeinOpenInterest": 0, "totalTradedVolume": 0, "impliedVolatility": 0, "lastPrice": 0, "change": 0, "pChange": 0, "totalBuyQuantity": 280000, "totalSellQuantity": 2170000, "bidQty": 140000, "bidprice": 1.7, "askQty": 2100000, "askPrice": 6.5, "underlyingValue": 7.2}}, {"strikePrice": 5, "expiryDate": "23-Feb-2023", "CE": {"strikePrice": 5, "expiryDate": "23-Feb-2023", "underlying": "IDEA", "identifier": "OPTSTKIDEA23-02-2023CE5.00", "openInterest": 0, "changeinOpenInterest": 0, "pchangeinOpenInterest": 0, "totalTradedVolume": 0, "impliedVolatility": 0, "lastPrice": 1.65, "change": 0, "pChange": 0, "totalBuyQuantity": 980000, "totalSellQuantity": 2310000, "bidQty": 140000, "bidprice": 1.05, "askQty": 140000, "askPrice": 4.45, "underlyingValue": 7.2}, "PE": {"strikePrice": 5, "expiryDate": "23-Feb-2023", "underlying": "IDEA", "identifier": "OPTSTKIDEA23-02-2023PE5.00", "openInterest": 214, "changeinOpenInterest": 0, "pchangeinOpenInterest": 0, "totalTradedVolume": 1, "impliedVolatility": 197.58, "lastPrice": 0.05, "change": 0, "pChange": 0, "totalBuyQuantity": 0, "totalSellQuantity": 11130000, "bidQty": 0, "bidprice": 0, "askQty": 8050000, "askPrice": 0.05, "underlyingValue": 7.2}}, {"strikePrice": 6, "expiryDate": "23-Feb-2023", "CE": {"strikePrice": 6, "expiryDate": "23-Feb-2023", "underlying": "IDEA", "identifier": "OPTSTKIDEA23-02-2023CE6.00", "openInterest": 102, "changeinOpenInterest": 5, "pchangeinOpenInterest": 5.154639175257732, "totalTradedVolume": 58, "impliedVolatility": 108.9, "lastPrice": 1.25, "change": -0.25, "pChange": -16.666666666666664, "totalBuyQuantity": 10500000, "totalSellQuantity": 2590000, "bidQty": 1960000, "bidprice": 1.15, "askQty": 350000, "askPrice": 1.3, "underlyingValue": 7.2}, "PE": {"strikePrice": 6, "expiryDate": "23-Feb-2023", "underlying": "IDEA", "identifier": "OPTSTKIDEA23-02-2023PE6.00", "openInterest": 607, "changeinOpenInterest": 35, "pchangeinOpenInterest": 6.118881118881119, "totalTradedVolume": 38, "impliedVolatility": 115.56, "lastPrice": 0.05, "change": 0, "pChange": 0, "totalBuyQuantity": 0, "totalSellQuantity": 39060000, "bidQty": 0, "bidprice": 0, "askQty": 22400000, "askPrice": 0.05, "underlyingValue": 7.2}}, {"strikePrice": 7, "expiryDate": "23-Feb-2023", "PE": {"strikePrice": 7, "expiryDate": "23-Feb-2023", "underlying": "IDEA", "identifier": "OPTSTKIDEA23-02-2023PE7.00", "openInterest": 640, "changeinOpenInterest": -237, "pchangeinOpenInterest": -27.02394526795895, "totalTradedVolume": 1539, "impliedVolatility": 51.56, "lastPrice": 0.1, "change": 0, "pChange": 0, "totalBuyQuantity": 46620000, "totalSellQuantity": 35840000, "bidQty": 46620000, "bidprice": 0.05, "askQty": 4200000, "askPrice": 0.1, "underlyingValue": 7.2}, "CE": {"strikePrice": 7, "expiryDate": "23-Feb-2023", "underlying": "IDEA", "identifier": "OPTSTKIDEA23-02-2023CE7.00", "openInterest": 469, "changeinOpenInterest": 92, "pchangeinOpenInterest": 24.40318302387268, "totalTradedVolume": 445, "impliedVolatility": 48.02, "lastPrice": 0.3, "change": -0.25000000000000006, "pChange": -45.45454545454546, "totalBuyQuantity": 25550000, "totalSellQuantity": 6860000, "bidQty": 2730000, "bidprice": 0.25, "askQty": 910000, "askPrice": 0.3, "underlyingValue": 7.2}}, {"strikePrice": 8, "expiryDate": "23-Feb-2023", "PE": {"strikePrice": 8, "expiryDate": "23-Feb-2023", "underlying": "IDEA", "identifier": "OPTSTKIDEA23-02-2023PE8.00", "openInterest": 741, "changeinOpenInterest": -88, "pchangeinOpenInterest": -10.615199034981906, "totalTradedVolume": 182, "impliedVolatility": 52.09, "lastPrice": 0.8, "change": 0.20000000000000007, "pChange": 33.33333333333335, "totalBuyQuantity": 14070000, "totalSellQuantity": 6720000, "bidQty": 140000, "bidprice": 0.8, "askQty": 70000, "askPrice": 0.85, "underlyingValue": 7.2}, "CE": {"strikePrice": 8, "expiryDate": "23-Feb-2023", "underlying": "IDEA", "identifier": "OPTSTKIDEA23-02-2023CE8.00", "openInterest": 1288, "changeinOpenInterest": -113, "pchangeinOpenInterest": -8.065667380442541, "totalTradedVolume": 1167, "impliedVolatility": 74, "lastPrice": 0.05, "change": -0.05, "pChange": -50, "totalBuyQuantity": 1260000, "totalSellQuantity": 60900000, "bidQty": 1260000, "bidprice": 0.05, "askQty": 35700000, "askPrice": 0.1, "underlyingValue": 7.2}}, {"strikePrice": 9, "expiryDate": "23-Feb-2023", "CE": {"strikePrice": 9, "expiryDate": "23-Feb-2023", "underlying": "IDEA", "identifier": "OPTSTKIDEA23-02-2023CE9.00", "openInterest": 1641, "changeinOpenInterest": 14, "pchangeinOpenInterest": 0.860479409956976, "totalTradedVolume": 64, "impliedVolatility": 125.6, "lastPrice": 0.05, "change": 0, "pChange": 0, "totalBuyQuantity": 0, "totalSellQuantity": 48720000, "bidQty": 0, "bidprice": 0, "askQty": 32340000, "askPrice": 0.05, "underlyingValue": 7.2}, "PE": {"strikePrice": 9, "expiryDate": "23-Feb-2023", "underlying": "IDEA", "identifier": "OPTSTKIDEA23-02-2023PE9.00", "openInterest": 235, "changeinOpenInterest": -53, "pchangeinOpenInterest": -18.40277777777778, "totalTradedVolume": 75, "impliedVolatility": 96.8, "lastPrice": 1.8, "change": 0.25, "pChange": 16.129032258064516, "totalBuyQuantity": 8050000, "totalSellQuantity": 6020000, "bidQty": 280000, "bidprice": 1.75, "askQty": 280000, "askPrice": 1.85, "underlyingValue": 7.2}}, {"strikePrice": 10, "expiryDate": "23-Feb-2023", "PE": {"strikePrice": 10, "expiryDate": "23-Feb-2023", "underlying": "IDEA", "identifier": "OPTSTKIDEA23-02-2023PE10.00", "openInterest": 52, "changeinOpenInterest": 0, "pchangeinOpenInterest": 0, "totalTradedVolume": 0, "impliedVolatility": 0, "lastPrice": 2.2, "change": 0, "pChange": 0, "totalBuyQuantity": 3290000, "totalSellQuantity": 280000, "bidQty": 70000, "bidprice": 2.75, "askQty": 140000, "askPrice": 4.6, "underlyingValue": 7.2}, "CE": {"strikePrice": 10, "expiryDate": "23-Feb-2023", "underlying": "IDEA", "identifier": "OPTSTKIDEA23-02-2023CE10.00", "openInterest": 1336, "changeinOpenInterest": 6, "pchangeinOpenInterest": 0.45112781954887216, "totalTradedVolume": 15, "impliedVolatility": 167.11, "lastPrice": 0.05, "change": 0, "pChange": 0, "totalBuyQuantity": 0, "totalSellQuantity": 34720000, "bidQty": 0, "bidprice": 0, "askQty": 24290000, "askPrice": 0.05, "underlyingValue": 7.2}}, {"strikePrice": 11, "expiryDate": "23-Feb-2023", "PE": {"strikePrice": 11, "expiryDate": "23-Feb-2023", "underlying": "IDEA", "identifier": "OPTSTKIDEA23-02-2023PE11.00", "openInterest": 1, "changeinOpenInterest": 0, "pchangeinOpenInterest": 0, "totalTradedVolume": 0, "impliedVolatility": 0, "lastPrice": 3.85, "change": 0, "pChange": 0, "totalBuyQuantity": 980000, "totalSellQuantity": 210000, "bidQty": 840000, "bidprice": 1.05, "askQty": 210000, "askPrice": 6.5, "underlyingValue": 7.2}, "CE": {"strikePrice": 11, "expiryDate": "23-Feb-2023", "underlying": "IDEA", "identifier": "OPTSTKIDEA23-02-2023CE11.00", "openInterest": 463, "changeinOpenInterest": 3, "pchangeinOpenInterest": 0.6521739130434783, "totalTradedVolume": 3, "impliedVolatility": 202.38, "lastPrice": 0.05, "change": 0, "pChange": 0, "totalBuyQuantity": 0, "totalSellQuantity": 16730000, "bidQty": 0, "bidprice": 0, "askQty": 13230000, "askPrice": 0.05, "underlyingValue": 7.2}}, {"strikePrice": 12, "expiryDate": "23-Feb-2023", "PE": {"strikePrice": 12, "expiryDate": "23-Feb-2023", "underlying": "IDEA", "identifier": "OPTSTKIDEA23-02-2023PE12.00", "openInterest": 0, "changeinOpenInterest": 0, "pchangeinOpenInterest": 0, "totalTradedVolume": 0, "impliedVolatility": 0, "lastPrice": 0, "change": 0, "pChange": 0, "totalBuyQuantity": 280000, "totalSellQuantity": 210000, "bidQty": 140000, "bidprice": 2.6, "askQty": 210000, "askPrice": 7.5, "underlyingValue": 7.2}, "CE": {"strikePrice": 12, "expiryDate": "23-Feb-2023", "underlying": "IDEA", "identifier": "OPTSTKIDEA23-02-2023CE12.00", "openInterest": 358, "changeinOpenInterest": 0, "pchangeinOpenInterest": 0, "totalTradedVolume": 0, "impliedVolatility": 0, "lastPrice": 0.05, "change": 0, "pChange": 0, "totalBuyQuantity": 0, "totalSellQuantity": 11130000, "bidQty": 0, "bidprice": 0, "askQty": 8680000, "askPrice": 0.05, "underlyingValue": 7.2}}, {"strikePrice": 13, "expiryDate": "23-Feb-2023", "PE": {"strikePrice": 13, "expiryDate": "23-Feb-2023", "underlying": "IDEA", "identifier": "OPTSTKIDEA23-02-2023PE13.00", "openInterest": 1, "changeinOpenInterest": 0, "pchangeinOpenInterest": 0, "totalTradedVolume": 0, "impliedVolatility": 0, "lastPrice": 5.55, "change": 0, "pChange": 0, "totalBuyQuantity": 2380000, "totalSellQuantity": 420000, "bidQty": 70000, "bidprice": 5.4, "askQty": 140000, "askPrice": 6.2, "underlyingValue": 7.2}, "CE": {"strikePrice": 13, "expiryDate": "23-Feb-2023", "underlying": "IDEA", "identifier": "OPTSTKIDEA23-02-2023CE13.00", "openInterest": 196, "changeinOpenInterest": 1, "pchangeinOpenInterest": 0.5128205128205128, "totalTradedVolume": 1, "impliedVolatility": 260.61, "lastPrice": 0.05, "change": 0, "pChange": 0, "totalBuyQuantity": 0, "totalSellQuantity": 5950000, "bidQty": 0, "bidprice": 0, "askQty": 3640000, "askPrice": 0.05, "underlyingValue": 7.2}}, {"strikePrice": 14, "expiryDate": "23-Feb-2023", "PE": {"strikePrice": 14, "expiryDate": "23-Feb-2023", "underlying": "IDEA", "identifier": "OPTSTKIDEA23-02-2023PE14.00", "openInterest": 0, "changeinOpenInterest": 0, "pchangeinOpenInterest": 0, "totalTradedVolume": 0, "impliedVolatility": 0, "lastPrice": 0, "change": 0, "pChange": 0, "totalBuyQuantity": 2240000, "totalSellQuantity": 210000, "bidQty": 140000, "bidprice": 5.05, "askQty": 140000, "askPrice": 8.6, "underlyingValue": 7.2}, "CE": {"strikePrice": 14, "expiryDate": "23-Feb-2023", "underlying": "IDEA", "identifier": "OPTSTKIDEA23-02-2023CE14.00", "openInterest": 192, "changeinOpenInterest": 0, "pchangeinOpenInterest": 0, "totalTradedVolume": 0, "impliedVolatility": 0, "lastPrice": 0.05, "change": 0, "pChange": 0, "totalBuyQuantity": 0, "totalSellQuantity": 7280000, "bidQty": 0, "bidprice": 0, "askQty": 5110000, "askPrice": 0.05, "underlyingValue": 7.2}}], "CE": {"totOI": 6045, "totVol": 1753}, "PE": {"totOI": 2507, "totVol": 1835}}}